oligocompose/__init__.py
oligocompose/oligocompose.py
oligocompose-0.2.1.dist-info/METADATA
oligocompose-0.2.1.dist-info/WHEEL
oligocompose-0.2.1.dist-info/entry_points.txt
oligocompose-0.2.1.dist-info/licenses/LICENSE
oligocompose-0.2.1.dist-info/RECORD
