Metadata-Version: 2.3
Name: oligocompose
Version: 0.2.1
Summary: A package to automatically generate oligonucleotide library pool sequences
Project-URL: Homepage, https://github.com/JamieHeather/oligocompose
Project-URL: Bug Reports, https://github.com/JamieHeather/oligocompose/issues
Project-URL: Source, https://github.com/pypa/sampleproject/
Author-email: Jamie Heather <jheather@mgh.harvard.edu>
Classifier: License :: OSI Approved :: MIT License
Classifier: Operating System :: OS Independent
Classifier: Programming Language :: Python :: 3
Requires-Python: >=3.8
